mGenS/__init__.py
mGenS/func.py
mGenS-0.1.2.dist-info/LICENSE
mGenS-0.1.2.dist-info/METADATA
mGenS-0.1.2.dist-info/WHEEL
mGenS-0.1.2.dist-info/top_level.txt
mGenS-0.1.2.dist-info/RECORD
