Metadata-Version: 2.1
Name: mGenS
Version: 0.1.2
Summary: Support functions
Home-page: https://github.com/hathaaaway/mgens
Author: Hathaway Zhang
Author-email: hathawayzhang@gmail.com
Classifier: Programming Language :: Python :: 3
Classifier: License :: OSI Approved :: MIT License
Classifier: Operating System :: OS Independent
Requires-Python: >=3.6
License-File: LICENSE
